summary/__init__.py
summary/cli.py
summary/summary.py
csv_summary-0.1.2.dist-info/METADATA
csv_summary-0.1.2.dist-info/WHEEL
csv_summary-0.1.2.dist-info/entry_points.txt
csv_summary-0.1.2.dist-info/top_level.txt
csv_summary-0.1.2.dist-info/RECORD
