Metadata-Version: 2.1
Name: csv_summary
Version: 0.1.2
Summary: 指定したCSVファイルの統計情報を生成するパッケージ
Home-page: https://github.com/pika8911/csv-summary
Author: pika8911
Author-email: s2122043@stu.musashino-u.ac.jp
Classifier: Programming Language :: Python :: 3
Classifier: License :: OSI Approved :: MIT License
Classifier: Operating System :: OS Independent
Requires-Python: >=3.6
Requires-Dist: pandas
